{
  "version": "2.0",
  "pipeline_stage": "enriched",
  "title": " ForrestGump-MEG",
  "description": "ForrestGump-MEG is a multimodal neuroimaging dataset comprising magnetoencephalography (MEG) recordings from 11 subjects during passive viewing of a 2-hour audio-visual movie stimulus (Chinese-dubbed Forrest Gump), along with structural MRI data. The dataset includes raw 275-channel CTF MEG data, preprocessed MEG recordings with independent component analysis decomposition, anatomically preprocessed T1-weighted images, and MEG-MRI co-registration information. This resource enables investigation of neural dynamics during naturalistic audiovisual perception and brain-behavior relationships in ecologically valid contexts.",
  "methods_description": "MEG data were acquired using a 275-channel CTF system during movie watching. Preprocessing involved: (1) bad channel detection and removal, (2) high-pass filtering at 1 Hz to remove slow drifts, and (3) artifact removal using independent component analysis. Structural T1-weighted images were minimally preprocessed using fMRIPrep's anatomical pipeline with default settings. MEG-MRI co-registration and surface reconstruction were performed using MNE-BIDS and FreeSurfer.",
  "license": "CC0",
  "dataset_type": "raw",
  "authors": {
    "Xingyu Liu": {},
    "Yuxuan Dai": {},
    "Hailun Xie": {},
    "Zonglei Zhen": {}
  },
  "keywords": [
    {
      "term": "MEG"
    },
    {
      "term": "Magnetoencephalography",
      "subject_scheme": "MeSH",
      "value_uri": "http://id.nlm.nih.gov/mesh/D015225"
    },
    {
      "term": "movie watching"
    },
    {
      "term": "naturalistic stimuli"
    },
    {
      "term": "audiovisual perception"
    },
    {
      "term": "structural MRI"
    },
    {
      "term": "independent component analysis"
    },
    {
      "term": "Forrest Gump"
    },
    {
      "term": "CTF MEG"
    },
    {
      "term": "fMRIPrep"
    },
    {
      "term": "FreeSurfer"
    },
    {
      "term": "passive viewing"
    }
  ],
  "related_identifiers": [
    {
      "identifier": "https://github.com/nemarDatasets/on003633",
      "identifier_type": "URL",
      "relation_type": "IsDescribedBy"
    },
    {
      "identifier": "https://nemar.org/dataexplorer/detail?dataset_id=on003633",
      "identifier_type": "URL",
      "relation_type": "IsDescribedBy"
    },
    {
      "identifier": "10.18112/openneuro.ds003633",
      "identifier_type": "DOI",
      "relation_type": "IsVersionOf"
    },
    {
      "identifier": "10.18112/openneuro.ds000113",
      "identifier_type": "DOI",
      "relation_type": "References"
    },
    {
      "identifier": "10.18112/openneuro.ds003633.v1.0.3",
      "identifier_type": "DOI",
      "relation_type": "IsDerivedFrom"
    }
  ],
  "funding_references": [
    {
      "funder_name": "National Key R&D Program of China",
      "award_number": "2019YFA0709503"
    },
    {
      "funder_name": "National Natural Science Foundation of China",
      "award_number": "31771251"
    }
  ],
  "resource_type_general": "Dataset",
  "resource_type_specific": "Structural MRI Dataset",
  "modalities": [
    "anat",
    "meg"
  ],
  "sizes": [
    "165.7 GB (5350 files)"
  ],
  "formats": [
    ".2mm/README",
    ".3d",
    ".H",
    ".K",
    ".README",
    ".acq",
    ".annot",
    ".area",
    ".avg",
    ".avg_curv",
    ".avg_sulc",
    ".avg_thickness",
    ".bak",
    ".cfg",
    ".cls",
    ".cmd",
    ".crv",
    ".csv",
    ".ctab",
    ".curv",
    ".dat",
    ".de",
    ".defect_borders",
    ".defect_chull",
    ".defect_labels",
    ".done",
    ".ds/BadChannels",
    ".eeg",
    ".env",
    ".fif",
    ".flat",
    ".gii",
    ".gitattributes",
    ".gz",
    ".h5",
    ".hc",
    ".hist",
    ".inflated",
    ".inflated_avg",
    ".inflated_pre",
    ".infods",
    ".jacobian_white",
    ".json",
    ".label",
    ".left_right",
    ".local-copy",
    ".log",
    ".lta",
    ".m",
    ".m3z",
    ".md",
    ".meg4",
    ".mgh",
    ".mgz",
    ".mid",
    ".midthickness",
    ".mrk",
    ".newds",
    ".nofix",
    ".old",
    ".orig",
    ".orig_avg",
    ".pial",
    ".pial_avg",
    ".pial_semi_inflated",
    ".preaparc",
    ".py",
    ".reg",
    ".res4",
    ".seghead",
    ".segments",
    ".sh",
    ".smoothwm",
    ".sphere",
    ".stats",
    ".sulc",
    ".surf",
    ".thickness",
    ".touch",
    ".tsv",
    ".txt",
    ".volume",
    ".white",
    ".white_avg",
    ".xfm",
    ".yml"
  ],
  "source_hash": "5cafb6ab59b5fb99c66b2ff9d92936c53583d70b60eec6797923d03e7410bb77"
}